{
  "aweme_id": "7378580678356618548",
  "video_title": "又是一次通过，儿豁",
  "comments": [
    {
      "aweme_id": "7378580678356618548",
      "cid": "7378628102081037097",
      "text": "你看看人家万柳柳[呲牙]",
      "create_time": "1717970738",
      "user_nickname": "长夏归序•初安",
      "user_avatar": "avatars/2024/a1a5a120ae3aa4b51572861a6d8f7d34.jpeg",
      "reply_comment_total": "16",
      "ip_label": "贵州",
      "create_time_str": "2024-06-09 22:05",
      "replies": [
        {
          "aweme_id": "7378580678356618548",
          "cid": "7378725866011231012",
          "reply_id": "7378628102081037097",
          "reply_to_reply_id": "0",
          "text": "你们这些假粉丝这明明是@大奇游戏解说⁸⁰⁰⁸",
          "create_time": "1717993498",
          "user_nickname": "长夏归序•初安",
          "user_avatar": "avatars/2024/a1a5a120ae3aa4b51572861a6d8f7d34.jpeg",
          "reply_to_username": "",
          "ip_label": "贵州",
          "create_time_str": "2024-06-10 04:24"
        },
        {
          "aweme_id": "7378580678356618548",
          "cid": "7378674343398490906",
          "reply_id": "7378628102081037097",
          "reply_to_reply_id": "0",
          "text": "这不是二哥吗[发呆]",
          "create_time": "1717981501",
          "user_nickname": "柚子",
          "user_avatar": "avatars/2024/ef22b5b3c424a3949ede4d92397db4c6.jpeg",
          "reply_to_username": "",
          "ip_label": "陕西",
          "create_time_str": "2024-06-10 01:05"
        },
        {
          "aweme_id": "7378580678356618548",
          "cid": "7378677171327484712",
          "reply_id": "7378628102081037097",
          "reply_to_reply_id": "0",
          "text": "这是贝小呆瓜",
          "create_time": "1717982159",
          "user_nickname": "嬴政",
          "user_avatar": "avatars/2024/04ad3f3a2900abe5555fb97713c568e8.jpeg",
          "reply_to_username": "",
          "ip_label": "江苏",
          "create_time_str": "2024-06-10 01:15"
        },
        {
          "aweme_id": "7378580678356618548",
          "cid": "7378687757990069029",
          "reply_id": "7378628102081037097",
          "reply_to_reply_id": "0",
          "text": "这明明是王分寸",
          "create_time": "1717984625",
          "user_nickname": "空白格²⁶¹⁸",
          "user_avatar": "avatars/2024/909fe9abf2f952b7d53920fdf08c79c2.jpeg",
          "reply_to_username": "",
          "ip_label": "江苏",
          "create_time_str": "2024-06-10 01:57"
        },
        {
          "aweme_id": "7378580678356618548",
          "cid": "7378714484511064867",
          "reply_id": "7378628102081037097",
          "reply_to_reply_id": "0",
          "text": "你是假粉丝吧，这明明是贝小呆瓜",
          "create_time": "1717990847",
          "user_nickname": "蒋不明白",
          "user_avatar": "avatars/2024/00f439215c60c0812139b9fe4f44a517.jpeg",
          "reply_to_username": "",
          "ip_label": "广东",
          "create_time_str": "2024-06-10 03:40"
        },
        {
          "aweme_id": "7378580678356618548",
          "cid": "7378718351087928115",
          "reply_id": "7378628102081037097",
          "reply_to_reply_id": "0",
          "text": "那是蛙宝蛙宝蛙宝OK",
          "create_time": "1717991746",
          "user_nickname": "用户1478901188436",
          "user_avatar": "avatars/2024/52af610828563897244185f21cbaa07b.jpeg",
          "reply_to_username": "",
          "ip_label": "安徽",
          "create_time_str": "2024-06-10 03:55"
        },
        {
          "aweme_id": "7378580678356618548",
          "cid": "7379429193422324507",
          "reply_id": "7378628102081037097",
          "reply_to_reply_id": "0",
          "text": "才圆圆：我跟你们有仇？一个不带提我的！[尬笑]",
          "create_time": "1718157256",
          "user_nickname": "时来运转",
          "user_avatar": "avatars/2024/ae3122e5f0ceb332da07586ed48cbf1a.jpeg",
          "reply_to_username": "",
          "ip_label": "四川",
          "create_time_str": "2024-06-12 01:54"
        },
        {
          "aweme_id": "7378580678356618548",
          "cid": "7378639877984502566",
          "reply_id": "7378628102081037097",
          "reply_to_reply_id": "0",
          "text": "这是蛙宝",
          "create_time": "1717973478",
          "user_nickname": "拜君仙⁹⁰⁹²⁷",
          "user_avatar": "avatars/2024/5ad5c3425562c4504c31663066d0145f.jpeg",
          "reply_to_username": "",
          "ip_label": "黑龙江",
          "create_time_str": "2024-06-09 22:51"
        },
        {
          "aweme_id": "7378580678356618548",
          "cid": "7378659080446952233",
          "reply_id": "7378628102081037097",
          "reply_to_reply_id": "0",
          "text": "[捂脸]",
          "create_time": "1717977947",
          "user_nickname": "巅风",
          "user_avatar": "avatars/2024/ad74cb27ce42a6db2ba27e77d0614c30.jpeg",
          "reply_to_username": "",
          "ip_label": "四川",
          "create_time_str": "2024-06-10 00:05"
        },
        {
          "aweme_id": "7378580678356618548",
          "cid": "7378669119523242771",
          "reply_id": "7378628102081037097",
          "reply_to_reply_id": "0",
          "text": "这是张全蛋本人，你们啥眼神啊",
          "create_time": "1717980287",
          "user_nickname": "闲丝达",
          "user_avatar": "avatars/2024/050b41558e776a7b66432bb2d06c5dde.jpeg",
          "reply_to_username": "",
          "ip_label": "海南",
          "create_time_str": "2024-06-10 00:44"
        },
        {
          "aweme_id": "7378580678356618548",
          "cid": "7378671783887274788",
          "reply_id": "7378628102081037097",
          "reply_to_reply_id": "0",
          "text": "这不是贝贝吗[看]",
          "create_time": "1717980907",
          "user_nickname": "小刘",
          "user_avatar": "avatars/2024/f176c06d727d0cb464f780a8f7bac937.jpeg",
          "reply_to_username": "",
          "ip_label": "浙江",
          "create_time_str": "2024-06-10 00:55"
        },
        {
          "aweme_id": "7378580678356618548",
          "cid": "7378672263362888488",
          "reply_id": "7378628102081037097",
          "reply_to_reply_id": "0",
          "text": "明明是蛙宝",
          "create_time": "1717981016",
          "user_nickname": "没故事也不喝酒",
          "user_avatar": "avatars/2024/866c5459002cf8462e1501126a3fad44.jpeg",
          "reply_to_username": "",
          "ip_label": "浙江",
          "create_time_str": "2024-06-10 00:56"
        },
        {
          "aweme_id": "7378580678356618548",
          "cid": "7378685056070599459",
          "reply_id": "7378628102081037097",
          "reply_to_reply_id": "0",
          "text": "小青蛙，跳的非常迷人",
          "create_time": "1717983997",
          "user_nickname": "금류年",
          "user_avatar": "avatars/2024/02256b1228e16431f8de8c24af77252c.jpeg",
          "reply_to_username": "",
          "ip_label": "四川",
          "create_time_str": "2024-06-10 01:46"
        },
        {
          "aweme_id": "7378580678356618548",
          "cid": "7378688289568752399",
          "reply_id": "7378628102081037097",
          "reply_to_reply_id": "0",
          "text": "你个假粉丝，这是蛙宝好不好[大笑]",
          "create_time": "1717984750",
          "user_nickname": "⁸⁰永荳⁰⁸",
          "user_avatar": "avatars/2024/91483cf1b63767d992054d059937a35b.jpeg",
          "reply_to_username": "",
          "ip_label": "青海",
          "create_time_str": "2024-06-10 01:59"
        },
        {
          "aweme_id": "7378580678356618548",
          "cid": "7379839374027359039",
          "reply_id": "7378628102081037097",
          "reply_to_reply_id": "0",
          "text": "这是我老婆贝贝什么柳柳",
          "create_time": "1718252757",
          "user_nickname": "小噜宝(>^ω^<)",
          "user_avatar": "avatars/2024/da92e8b88dadb65f2bf5fd7196496822.jpeg",
          "reply_to_username": "",
          "ip_label": "福建",
          "create_time_str": "2024-06-13 04:25"
        },
        {
          "aweme_id": "7378580678356618548",
          "cid": "7381275131904131851",
          "reply_id": "7378628102081037097",
          "reply_to_reply_id": "0",
          "text": "",
          "create_time": "1718587047",
          "user_nickname": "张君宝.",
          "user_avatar": "avatars/2024/4b7faade8f57802a1d7a497c3a81b9b4.jpeg",
          "reply_to_username": "",
          "ip_label": "广东",
          "create_time_str": "2024-06-17 01:17"
        }
      ],
      "reply_count": 16
    },
    {
      "aweme_id": "7378580678356618548",
      "cid": "7378650060391793443",
      "text": "我还纳闷这种游戏究竟是靠什么受众群体来支撑的[捂脸][捂脸][捂脸][捂脸][捂脸][捂脸][捂脸][捂脸][捂脸]",
      "create_time": "1717975851",
      "user_nickname": "资州府小钻风⁵¹⁰⁷⁴",
      "user_avatar": "avatars/2024/fbaef8e7eb613c5e17cc44992894f881.jpeg",
      "reply_comment_total": "0",
      "ip_label": "四川",
      "create_time_str": "2024-06-09 23:30",
      "replies": [],
      "reply_count": 0
    },
    {
      "aweme_id": "7378580678356618548",
      "cid": "7378586237290251027",
      "text": "很难吗[噢买尬]",
      "create_time": "1717961006",
      "user_nickname": "用户9853312396296",
      "user_avatar": "avatars/2024/2f0c1d624595a7527daa35a19cf309de.jpeg",
      "reply_comment_total": "1",
      "ip_label": "广东",
      "create_time_str": "2024-06-09 19:23",
      "replies": [
        {
          "aweme_id": "7378580678356618548",
          "cid": "7378703923651609354",
          "reply_id": "7378586237290251027",
          "reply_to_reply_id": "0",
          "text": "这啥游戏？[看]",
          "create_time": "1717988388",
          "user_nickname": "世弌",
          "user_avatar": "avatars/2024/f8d4f53ed73f4e04ec6f3634f2023635.jpeg",
          "reply_to_username": "",
          "ip_label": "安徽",
          "create_time_str": "2024-06-10 02:59"
        }
      ],
      "reply_count": 1
    },
    {
      "aweme_id": "7378580678356618548",
      "cid": "7378582716118434598",
      "text": "?????不睡觉有本事你就开播",
      "create_time": "1717960188",
      "user_nickname": "设计橙",
      "user_avatar": "avatars/2024/49332a18b772a6fbe8c935cca860c217.jpeg",
      "reply_comment_total": "0",
      "ip_label": "广东",
      "create_time_str": "2024-06-09 19:09",
      "replies": [],
      "reply_count": 0
    },
    {
      "aweme_id": "7378580678356618548",
      "cid": "7378631749901959945",
      "text": "",
      "create_time": "1717971590",
      "user_nickname": "有你陪我⁵¹⁰⁷⁴",
      "user_avatar": "avatars/2024/4e161febc65a2dca2756f06792e9c857.jpeg",
      "reply_comment_total": "1",
      "ip_label": "安徽",
      "create_time_str": "2024-06-09 22:19",
      "replies": [
        {
          "aweme_id": "7378580678356618548",
          "cid": "7378826206093542171",
          "reply_id": "7378631749901959945",
          "reply_to_reply_id": "0",
          "text": "",
          "create_time": "1718016858",
          "user_nickname": "念白☀",
          "user_avatar": "avatars/2024/9f07e9089b7902a13b24c3180d7bad98.jpeg",
          "reply_to_username": "",
          "ip_label": "北京",
          "create_time_str": "2024-06-10 10:54"
        }
      ],
      "reply_count": 1
    },
    {
      "aweme_id": "7378580678356618548",
      "cid": "7378602426578436902",
      "text": "这该死的天赋[看]",
      "create_time": "1717964774",
      "user_nickname": "星✨河 ⁵¹⁰⁷⁴",
      "user_avatar": "avatars/2024/0c9d1aa454d440f0cb7c2851be85a678.jpeg",
      "reply_comment_total": "0",
      "ip_label": "安徽",
      "create_time_str": "2024-06-09 20:26",
      "replies": [],
      "reply_count": 0
    },
    {
      "aweme_id": "7378580678356618548",
      "cid": "7378848265674064666",
      "text": "[九转大肠]飞上去找小范大人呀？？？",
      "create_time": "1718021994",
      "user_nickname": "花哥威武",
      "user_avatar": "avatars/2024/bacafbe901652caef9571759e2be901f.jpeg",
      "reply_comment_total": "0",
      "ip_label": "广东",
      "create_time_str": "2024-06-10 12:19",
      "replies": [],
      "reply_count": 0
    },
    {
      "aweme_id": "7378580678356618548",
      "cid": "7378844867621290779",
      "text": "蹦了十一次。全蛋 找到对象啦[泪奔][尬笑]",
      "create_time": "1718021203",
      "user_nickname": "延吉足悦泡脚店",
      "user_avatar": "avatars/2024/17755c7712cd7f018f357fbaeec6bee3.jpeg",
      "reply_comment_total": "0",
      "ip_label": "吉林",
      "create_time_str": "2024-06-10 12:06",
      "replies": [],
      "reply_count": 0
    },
    {
      "aweme_id": "7378580678356618548",
      "cid": "7378711183782527771",
      "text": "这个游戏叫 张老黑历经千辛万苦找男人[捂脸]",
      "create_time": "1717990078",
      "user_nickname": "给幾 ⁵¹⁰⁷⁴",
      "user_avatar": "avatars/2024/4592a192efb0251f1149691f9b1e5b59.jpeg",
      "reply_comment_total": "0",
      "ip_label": "河北",
      "create_time_str": "2024-06-10 03:27",
      "replies": [],
      "reply_count": 0
    },
    {
      "aweme_id": "7378580678356618548",
      "cid": "7378692218489996083",
      "text": "[尬笑]",
      "create_time": "1717985662",
      "user_nickname": "66666",
      "user_avatar": "avatars/2024/fcdf644588a55a50a8232365b5d86944.jpeg",
      "reply_comment_total": "0",
      "ip_label": "北京",
      "create_time_str": "2024-06-10 02:14",
      "replies": [],
      "reply_count": 0
    },
    {
      "aweme_id": "7378580678356618548",
      "cid": "7378664540907111187",
      "text": "你得有多无聊，玩上这小游戏了[呲牙]赶快找个男朋友吧",
      "create_time": "1717979219",
      "user_nickname": "四川靓号之家",
      "user_avatar": "avatars/2024/aee24fab073f963d888811d23b755c26.jpeg",
      "reply_comment_total": "0",
      "ip_label": "四川",
      "create_time_str": "2024-06-10 00:26",
      "replies": [],
      "reply_count": 0
    },
    {
      "aweme_id": "7378580678356618548",
      "cid": "7378597906175755018",
      "text": "",
      "create_time": "1717963724",
      "user_nickname": "🌈🌈🌈高压旋喷桩队⁸⁰⁰⁸",
      "user_avatar": "avatars/2024/6c71bd1cc1567bcffabd20a3731a5e48.jpeg",
      "reply_comment_total": "0",
      "ip_label": "广东",
      "create_time_str": "2024-06-09 20:08",
      "replies": [],
      "reply_count": 0
    },
    {
      "aweme_id": "7378580678356618548",
      "cid": "7378585973997519631",
      "text": "看着寨主想找老公了，不想做单身狗了",
      "create_time": "1717960952",
      "user_nickname": "一片红枫叶",
      "user_avatar": "avatars/2024/066fa5e0a66ef5733938b5beb659a630.jpeg",
      "reply_comment_total": "0",
      "ip_label": "浙江",
      "create_time_str": "2024-06-09 19:22",
      "replies": [],
      "reply_count": 0
    },
    {
      "aweme_id": "7378580678356618548",
      "cid": "7378584804939612937",
      "text": "这是有多无聊啊[捂脸][捂脸][捂脸][捂脸]",
      "create_time": "1717960670",
      "user_nickname": "阿亮",
      "user_avatar": "avatars/2024/79a9ac59ba95c480e8e7488d943c8e31.jpeg",
      "reply_comment_total": "0",
      "ip_label": "广东",
      "create_time_str": "2024-06-09 19:17",
      "replies": [],
      "reply_count": 0
    },
    {
      "aweme_id": "7378580678356618548",
      "cid": "7378583336673264422",
      "text": "我觉得背景音乐好挺适合你的 哈哈哈哈哈",
      "create_time": "1717960328",
      "user_nickname": "D H C .",
      "user_avatar": "avatars/2024/337de0ac4ae961bdf9e98bbd728ee1e7.jpeg",
      "reply_comment_total": "0",
      "ip_label": "四川",
      "create_time_str": "2024-06-09 19:12",
      "replies": [],
      "reply_count": 0
    },
    {
      "aweme_id": "7378580678356618548",
      "cid": "7380714798743241512",
      "text": "君雅，能将我从你大号黑名单中放出来啊，谢谢哦： 祝您今年比找到白马王子，直播事业蒸蒸日上[玫瑰][玫瑰][玫瑰]",
      "create_time": "1718456581",
      "user_nickname": "旅途的迪迪",
      "user_avatar": "avatars/2024/865544c5e701a238f12ff9331e62b66a.jpeg",
      "reply_comment_total": "0",
      "ip_label": "上海",
      "create_time_str": "2024-06-15 13:03",
      "replies": [],
      "reply_count": 0
    },
    {
      "aweme_id": "7378580678356618548",
      "cid": "7380607345665409832",
      "text": "真搞笑，直播间开几句玩笑，你们家管理就直接踢出直播间，封了号，好歹也是9级灯牌，看了这么久了，玩笑都开不起，笑话",
      "create_time": "1718431563",
      "user_nickname": "总有刁民想害振",
      "user_avatar": "avatars/2024/e934eda73034a9657a5e8cf00d522c63.jpeg",
      "reply_comment_total": "0",
      "ip_label": "江苏",
      "create_time_str": "2024-06-15 06:06",
      "replies": [],
      "reply_count": 0
    },
    {
      "aweme_id": "7378580678356618548",
      "cid": "7380304407247979283",
      "text": "你是找不到事情干",
      "create_time": "1718361029",
      "user_nickname": "迟遇",
      "user_avatar": "avatars/2024/3cf958814b13d514e162c1fd3194b704.jpeg",
      "reply_comment_total": "0",
      "ip_label": "四川",
      "create_time_str": "2024-06-14 10:30",
      "replies": [],
      "reply_count": 0
    },
    {
      "aweme_id": "7378580678356618548",
      "cid": "7379623082589897524",
      "text": "跳舞吧[尬笑]",
      "create_time": "1718202396",
      "user_nickname": "@🌈杰",
      "user_avatar": "avatars/2024/cf6d5f35a4a7874532fbeae7b3a90869.jpeg",
      "reply_comment_total": "0",
      "ip_label": "黑龙江",
      "create_time_str": "2024-06-12 14:26",
      "replies": [],
      "reply_count": 0
    },
    {
      "aweme_id": "7378580678356618548",
      "cid": "7379240590736720655",
      "text": "思想与行动完美结合[赞][赞][赞]",
      "create_time": "1718113339",
      "user_nickname": "智慧·⁸¹⁶",
      "user_avatar": "avatars/2024/7de06224df22d1bf7500fc9c14b9ac4e.jpeg",
      "reply_comment_total": "0",
      "ip_label": "浙江",
      "create_time_str": "2024-06-11 13:42",
      "replies": [],
      "reply_count": 0
    },
    {
      "aweme_id": "7378580678356618548",
      "cid": "7379151199071552283",
      "text": "[捂脸]",
      "create_time": "1718092528",
      "user_nickname": "宝 ້",
      "user_avatar": "avatars/2024/d2b8b36ccd87ff6b8953c075a2431b5b.jpeg",
      "reply_comment_total": "0",
      "ip_label": "福建",
      "create_time_str": "2024-06-11 07:55",
      "replies": [],
      "reply_count": 0
    },
    {
      "aweme_id": "7378580678356618548",
      "cid": "7379087789109150473",
      "text": "你真是不挑游戏啊",
      "create_time": "1718077763",
      "user_nickname": "拉菲重生",
      "user_avatar": "avatars/2024/f2592095d452c9c01a714c70fb041551.jpeg",
      "reply_comment_total": "0",
      "ip_label": "湖北",
      "create_time_str": "2024-06-11 03:49",
      "replies": [],
      "reply_count": 0
    },
    {
      "aweme_id": "7378580678356618548",
      "cid": "7379011813802296091",
      "text": "就是说无聊到这个程度了吗 要不让才圆圆给你把把脉看看？[发呆]",
      "create_time": "1718060081",
      "user_nickname": "王鲜森",
      "user_avatar": "avatars/2024/d0478f0bba86c1a361707e79f7ae161b.jpeg",
      "reply_comment_total": "0",
      "ip_label": "广东",
      "create_time_str": "2024-06-10 22:54",
      "replies": [],
      "reply_count": 0
    },
    {
      "aweme_id": "7378580678356618548",
      "cid": "7378883209805955879",
      "text": "",
      "create_time": "1718030132",
      "user_nickname": "取经修勾",
      "user_avatar": "avatars/2024/bd62cca1f93b87043af3d97e8d1f1686.jpeg",
      "reply_comment_total": "0",
      "ip_label": "安徽",
      "create_time_str": "2024-06-10 14:35",
      "replies": [],
      "reply_count": 0
    },
    {
      "aweme_id": "7378580678356618548",
      "cid": "7378836732504687398",
      "text": "你好，张三岁[捂脸][捂脸][捂脸]",
      "create_time": "1718019309",
      "user_nickname": "时光⁸⁰⁰⁸",
      "user_avatar": "avatars/2024/b5bc6836513cba2d18a3d75c24a9529b.jpeg",
      "reply_comment_total": "0",
      "ip_label": "江苏",
      "create_time_str": "2024-06-10 11:35",
      "replies": [],
      "reply_count": 0
    },
    {
      "aweme_id": "7378580678356618548",
      "cid": "7378782645604451099",
      "text": "跟着节奏一起来",
      "create_time": "1718006717",
      "user_nickname": "♪桔梨萝柚♪",
      "user_avatar": "avatars/2024/68fb824b4c4d6e3e9fada8718cf2c64c.jpeg",
      "reply_comment_total": "0",
      "ip_label": "广西",
      "create_time_str": "2024-06-10 08:05",
      "replies": [],
      "reply_count": 0
    },
    {
      "aweme_id": "7378580678356618548",
      "cid": "7378765004671894324",
      "text": "果然是老六[憨笑]",
      "create_time": "1718002610",
      "user_nickname": "小黑羊🐑",
      "user_avatar": "avatars/2024/38af2f80a2378a2b19d54a7eb6facd2a.jpeg",
      "reply_comment_total": "0",
      "ip_label": "上海",
      "create_time_str": "2024-06-10 06:56",
      "replies": [],
      "reply_count": 0
    },
    {
      "aweme_id": "7378580678356618548",
      "cid": "7378752845083001651",
      "text": "[抠鼻]",
      "create_time": "1717999778",
      "user_nickname": "²⁰²5张¹³₁₄๓᭄⁸ºº⁸",
      "user_avatar": "avatars/2024/fa42d8a016adb57a926f2a54f55b0a74.jpeg",
      "reply_comment_total": "0",
      "ip_label": "上海",
      "create_time_str": "2024-06-10 06:09",
      "replies": [],
      "reply_count": 0
    },
    {
      "aweme_id": "7378580678356618548",
      "cid": "7378741356154880783",
      "text": "这是有人了？",
      "create_time": "1717997105",
      "user_nickname": "寂寞在唱歌",
      "user_avatar": "avatars/2024/3d636ccd5848091aac6750cfd6d9c61b.jpeg",
      "reply_comment_total": "0",
      "ip_label": "辽宁",
      "create_time_str": "2024-06-10 05:25",
      "replies": [],
      "reply_count": 0
    },
    {
      "aweme_id": "7378580678356618548",
      "cid": "7378724856395744034",
      "text": "",
      "create_time": "1717993263",
      "user_nickname": "折耳根不腥",
      "user_avatar": "avatars/2024/7bd0abfa0a8751c94b00df65ae17c100.jpeg",
      "reply_comment_total": "0",
      "ip_label": "浙江",
      "create_time_str": "2024-06-10 04:21",
      "replies": [],
      "reply_count": 0
    },
    {
      "aweme_id": "7378580678356618548",
      "cid": "7378707752623014656",
      "text": "ok 给你点个赞[暗中观察]",
      "create_time": "1717989279",
      "user_nickname": "Heoxou",
      "user_avatar": "avatars/2024/94503b0966b29a6689258b27d00500af.jpeg",
      "reply_comment_total": "0",
      "ip_label": "广西",
      "create_time_str": "2024-06-10 03:14",
      "replies": [],
      "reply_count": 0
    },
    {
      "aweme_id": "7378580678356618548",
      "cid": "7378706652197716747",
      "text": "你是🈶️多无聊[捂脸][捂脸][捂脸]",
      "create_time": "1717989024",
      "user_nickname": "看海听㶡",
      "user_avatar": "avatars/2024/572cd29dae79192b2e78f7f1d06b7ec3.jpeg",
      "reply_comment_total": "0",
      "ip_label": "湖南",
      "create_time_str": "2024-06-10 03:10",
      "replies": [],
      "reply_count": 0
    },
    {
      "aweme_id": "7378580678356618548",
      "cid": "7378694929562944308",
      "text": "全蛋就是游戏天才[偷笑]",
      "create_time": "1717986296",
      "user_nickname": "ゞ编識ξ夢話ω",
      "user_avatar": "avatars/2024/cd3a5983be64c50e3b14d0450fe0a7f3.jpeg",
      "reply_comment_total": "0",
      "ip_label": "江西",
      "create_time_str": "2024-06-10 02:24",
      "replies": [],
      "reply_count": 0
    },
    {
      "aweme_id": "7378580678356618548",
      "cid": "7378694655481856807",
      "text": "张大房想男人想疯了[捂脸][捂脸][捂脸]",
      "create_time": "1717986231",
      "user_nickname": "用户9690567859289",
      "user_avatar": "avatars/2024/2f0c1d624595a7527daa35a19cf309de.jpeg",
      "reply_comment_total": "0",
      "ip_label": "贵州",
      "create_time_str": "2024-06-10 02:23",
      "replies": [],
      "reply_count": 0
    },
    {
      "aweme_id": "7378580678356618548",
      "cid": "7378690105088967474",
      "text": "",
      "create_time": "1717985169",
      "user_nickname": "“未来自己掌握”",
      "user_avatar": "avatars/2024/5e1c470285b7087739a4267f2b220496.jpeg",
      "reply_comment_total": "0",
      "ip_label": "浙江",
      "create_time_str": "2024-06-10 02:06",
      "replies": [],
      "reply_count": 0
    },
    {
      "aweme_id": "7378580678356618548",
      "cid": "7378688404714259240",
      "text": "充分演示了女追男隔层纱[看] 但是爱播却要不到微信[呲牙][呲牙][呲牙]",
      "create_time": "1717984775",
      "user_nickname": "秀才遇到兵",
      "user_avatar": "avatars/2024/9201a13d648eac3ee50f41b9d1756d2b.jpeg",
      "reply_comment_total": "0",
      "ip_label": "甘肃",
      "create_time_str": "2024-06-10 01:59",
      "replies": [],
      "reply_count": 0
    },
    {
      "aweme_id": "7378580678356618548",
      "cid": "7378686875420541706",
      "text": "张全蛋才三岁[捂脸]",
      "create_time": "1717984418",
      "user_nickname": "&无痕&",
      "user_avatar": "avatars/2024/fbc620a92d1c1700a31ca8e3ab65c0c2.jpeg",
      "reply_comment_total": "0",
      "ip_label": "上海",
      "create_time_str": "2024-06-10 01:53",
      "replies": [],
      "reply_count": 0
    },
    {
      "aweme_id": "7378580678356618548",
      "cid": "7378684181746189110",
      "text": "有男朋友就不会半夜三更的玩这种了[抠鼻][抠鼻][抠鼻][抠鼻]",
      "create_time": "1717983791",
      "user_nickname": "老农民A1",
      "user_avatar": "avatars/2024/ead9034c1e6ddc121e4da9452e284035.jpeg",
      "reply_comment_total": "0",
      "ip_label": "贵州",
      "create_time_str": "2024-06-10 01:43",
      "replies": [],
      "reply_count": 0
    },
    {
      "aweme_id": "7378580678356618548",
      "cid": "7378681869132825398",
      "text": "去游戏厅玩抓娃娃机吧 你有这个天赋",
      "create_time": "1717983253",
      "user_nickname": "赵懒懒",
      "user_avatar": "avatars/2024/d19b2e5410fe4205f74d477d7786ff69.jpeg",
      "reply_comment_total": "0",
      "ip_label": "山西",
      "create_time_str": "2024-06-10 01:34",
      "replies": [],
      "reply_count": 0
    },
    {
      "aweme_id": "7378580678356618548",
      "cid": "7378677911903666956",
      "text": "你这样其他人都不敢玩了[捂脸][捂脸][捂脸]",
      "create_time": "1717982332",
      "user_nickname": "柠檬心、薄荷情〆",
      "user_avatar": "avatars/2024/fb2d12ef3d55c720ad8f3a0a1456c596.jpeg",
      "reply_comment_total": "0",
      "ip_label": "四川",
      "create_time_str": "2024-06-10 01:18",
      "replies": [],
      "reply_count": 0
    },
    {
      "aweme_id": "7378580678356618548",
      "cid": "7378676151462707968",
      "text": "你是真的无聊[微笑]",
      "create_time": "1717981924",
      "user_nickname": "肚冰不喝热水",
      "user_avatar": "avatars/2024/90786cc7709b53438ffbe13d7f16b1a0.jpeg",
      "reply_comment_total": "0",
      "ip_label": "湖北",
      "create_time_str": "2024-06-10 01:12",
      "replies": [],
      "reply_count": 0
    },
    {
      "aweme_id": "7378580678356618548",
      "cid": "7378670799609316159",
      "text": "",
      "create_time": "1717980675",
      "user_nickname": "用户0384342990220",
      "user_avatar": "avatars/2024/2f0c1d624595a7527daa35a19cf309de.jpeg",
      "reply_comment_total": "0",
      "ip_label": "福建",
      "create_time_str": "2024-06-10 00:51",
      "replies": [],
      "reply_count": 0
    },
    {
      "aweme_id": "7378580678356618548",
      "cid": "7378668554490774309",
      "text": "啥啊[捂脸]",
      "create_time": "1717980152",
      "user_nickname": "许仙爱上了小倩",
      "user_avatar": "avatars/2024/46c835d24cb3133bdc9690b980a87e4a.jpeg",
      "reply_comment_total": "0",
      "ip_label": "四川",
      "create_time_str": "2024-06-10 00:42",
      "replies": [],
      "reply_count": 0
    },
    {
      "aweme_id": "7378580678356618548",
      "cid": "7378662807551968054",
      "text": "厉害了宝贝",
      "create_time": "1717978815",
      "user_nickname": "一介俗人ꫀꪝ.",
      "user_avatar": "avatars/2024/4623c00167395438880ba62209b0d621.jpeg",
      "reply_comment_total": "0",
      "ip_label": "山东",
      "create_time_str": "2024-06-10 00:20",
      "replies": [],
      "reply_count": 0
    },
    {
      "aweme_id": "7378580678356618548",
      "cid": "7378661651383862066",
      "text": "这游戏好沙雕[捂脸]",
      "create_time": "1717978547",
      "user_nickname": "♛小菜鸟",
      "user_avatar": "avatars/2024/df3c662d5ee50c92ceb154ae5a3138c2.jpeg",
      "reply_comment_total": "0",
      "ip_label": "广东",
      "create_time_str": "2024-06-10 00:15",
      "replies": [],
      "reply_count": 0
    },
    {
      "aweme_id": "7378580678356618548",
      "cid": "7378661489358570280",
      "text": "游戏天才教我儿子打游戏吧",
      "create_time": "1717978510",
      "user_nickname": "我要做靓仔",
      "user_avatar": "avatars/2024/cb622cdf47da4f6210ab17e6aff51997.jpeg",
      "reply_comment_total": "0",
      "ip_label": "江苏",
      "create_time_str": "2024-06-10 00:15",
      "replies": [],
      "reply_count": 0
    },
    {
      "aweme_id": "7378580678356618548",
      "cid": "7378661270175843091",
      "text": "这君雅，开始想男人了[鼓掌][鼓掌][鼓掌]",
      "create_time": "1717978458",
      "user_nickname": "舟山蜀峰厨房设备",
      "user_avatar": "avatars/2024/cac6477f46a66dee1f6ce45e35e96309.jpeg",
      "reply_comment_total": "0",
      "ip_label": "浙江",
      "create_time_str": "2024-06-10 00:14",
      "replies": [],
      "reply_count": 0
    },
    {
      "aweme_id": "7378580678356618548",
      "cid": "7378660632609260298",
      "text": "这是渴望爱情了[尬笑]",
      "create_time": "1717978310",
      "user_nickname": "秋灬",
      "user_avatar": "avatars/2024/0c9061088245038efe9434bb49bbc96f.jpeg",
      "reply_comment_total": "0",
      "ip_label": "四川",
      "create_time_str": "2024-06-10 00:11",
      "replies": [],
      "reply_count": 0
    },
    {
      "aweme_id": "7378580678356618548",
      "cid": "7378659750106497842",
      "text": "",
      "create_time": "1717978105",
      "user_nickname": "你好难哄！",
      "user_avatar": "avatars/2024/26cc50628febbe6300fa9316154d6314.jpeg",
      "reply_comment_total": "0",
      "ip_label": "河北",
      "create_time_str": "2024-06-10 00:08",
      "replies": [],
      "reply_count": 0
    },
    {
      "aweme_id": "7378580678356618548",
      "cid": "7378658992929817371",
      "text": "有没有和我一样想看全蛋被夹在中间的[偷笑][偷笑]",
      "create_time": "1717977929",
      "user_nickname": "༒。༒",
      "user_avatar": "avatars/2024/5620a9ec382c32080104334465b41d83.jpeg",
      "reply_comment_total": "0",
      "ip_label": "广东",
      "create_time_str": "2024-06-10 00:05",
      "replies": [],
      "reply_count": 0
    },
    {
      "aweme_id": "7378580678356618548",
      "cid": "7378656804614980352",
      "text": "不信[抠鼻]",
      "create_time": "1717977421",
      "user_nickname": "小王不会打球",
      "user_avatar": "avatars/2024/540a76daac399e1a5b9fe843adece377.jpeg",
      "reply_comment_total": "0",
      "ip_label": "重庆",
      "create_time_str": "2024-06-09 23:57",
      "replies": [],
      "reply_count": 0
    },
    {
      "aweme_id": "7378580678356618548",
      "cid": "7378656098196587279",
      "text": "单身狗想找男人了[捂脸]",
      "create_time": "1717977253",
      "user_nickname": "🌈林间捕风✨💫",
      "user_avatar": "avatars/2024/7d1f61ab5aafe85258d06c26f8a75f8e.jpeg",
      "reply_comment_total": "0",
      "ip_label": "上海",
      "create_time_str": "2024-06-09 23:54",
      "replies": [],
      "reply_count": 0
    },
    {
      "aweme_id": "7378580678356618548",
      "cid": "7378654843482997514",
      "text": "这有啥好炫耀的？",
      "create_time": "1717976961",
      "user_nickname": "用户8664324875650",
      "user_avatar": "avatars/2024/129b9fe401835420976b71eed1581064.jpeg",
      "reply_comment_total": "0",
      "ip_label": "山东",
      "create_time_str": "2024-06-09 23:49",
      "replies": [],
      "reply_count": 0
    },
    {
      "aweme_id": "7378580678356618548",
      "cid": "7378654835359187738",
      "text": "小女生",
      "create_time": "1717976960",
      "user_nickname": "用户2368743055046",
      "user_avatar": "avatars/2024/2f0c1d624595a7527daa35a19cf309de.jpeg",
      "reply_comment_total": "0",
      "ip_label": "广东",
      "create_time_str": "2024-06-09 23:49",
      "replies": [],
      "reply_count": 0
    },
    {
      "aweme_id": "7378580678356618548",
      "cid": "7378654239843025699",
      "text": "要是没跳上去没人搂是不是睡不着，[泪奔][泪奔][泪奔]",
      "create_time": "1717976821",
      "user_nickname": "张有才",
      "user_avatar": "avatars/2024/d113bfaf8095f5b032a0bc0f84878b8f.jpeg",
      "reply_comment_total": "0",
      "ip_label": "浙江",
      "create_time_str": "2024-06-09 23:47",
      "replies": [],
      "reply_count": 0
    },
    {
      "aweme_id": "7378580678356618548",
      "cid": "7378652441749455631",
      "text": "我居然看到最后了[看][看][看][看]",
      "create_time": "1717976403",
      "user_nickname": "二哥呀",
      "user_avatar": "avatars/2024/21971c3a68077b71a0090146f9b9235a.jpeg",
      "reply_comment_total": "0",
      "ip_label": "江苏",
      "create_time_str": "2024-06-09 23:40",
      "replies": [],
      "reply_count": 0
    },
    {
      "aweme_id": "7378580678356618548",
      "cid": "7378646682769179443",
      "text": "月亮不睡，你不睡。[尬笑]",
      "create_time": "1717975063",
      "user_nickname": "暮生·凉",
      "user_avatar": "avatars/2024/d370e7ee1f99803e35141ed7cd788440.jpeg",
      "reply_comment_total": "0",
      "ip_label": "广东",
      "create_time_str": "2024-06-09 23:17",
      "replies": [],
      "reply_count": 0
    },
    {
      "aweme_id": "7378580678356618548",
      "cid": "7378643379100369704",
      "text": "牛啊，这是没视频发个。应该像才老六学习发个跳舞的。",
      "create_time": "1717974295",
      "user_nickname": "༊ღ᭄飛ꦿ꯭飛꧔ꦿ᭄💞",
      "user_avatar": "avatars/2024/ddeb69615f7b2b2a46b016286392e9e7.jpeg",
      "reply_comment_total": "0",
      "ip_label": "湖北",
      "create_time_str": "2024-06-09 23:04",
      "replies": [],
      "reply_count": 0
    },
    {
      "aweme_id": "7378580678356618548",
      "cid": "7378639906208482074",
      "text": "[666][666][666][666][666][666][666][666][666][666][666]",
      "create_time": "1717973486",
      "user_nickname": "拜君仙⁹⁰⁹²⁷",
      "user_avatar": "avatars/2024/5ad5c3425562c4504c31663066d0145f.jpeg",
      "reply_comment_total": "0",
      "ip_label": "黑龙江",
      "create_time_str": "2024-06-09 22:51",
      "replies": [],
      "reply_count": 0
    },
    {
      "aweme_id": "7378580678356618548",
      "cid": "7378638234018513705",
      "text": "牙疼？",
      "create_time": "1717973097",
      "user_nickname": "初见†",
      "user_avatar": "avatars/2024/ec58f7e535d5c47b3d22328d11a71a44.jpeg",
      "reply_comment_total": "0",
      "ip_label": "河南",
      "create_time_str": "2024-06-09 22:44",
      "replies": [],
      "reply_count": 0
    },
    {
      "aweme_id": "7378580678356618548",
      "cid": "7378633130645701386",
      "text": "什么时候回归和平？",
      "create_time": "1717971910",
      "user_nickname": "漫漫长路",
      "user_avatar": "avatars/2024/5df72d6c967482a66ee1f424dce079cf.jpeg",
      "reply_comment_total": "0",
      "ip_label": "四川",
      "create_time_str": "2024-06-09 22:25",
      "replies": [],
      "reply_count": 0
    },
    {
      "aweme_id": "7378580678356618548",
      "cid": "7378632092178350900",
      "text": "没有头被夹住的截图吗[绿帽子]",
      "create_time": "1717971670",
      "user_nickname": "🚬ღ᭄辭ꦿ࿐",
      "user_avatar": "avatars/2024/feafbc7d59cf1eec529c549115fa98bf.jpeg",
      "reply_comment_total": "0",
      "ip_label": "山东",
      "create_time_str": "2024-06-09 22:21",
      "replies": [],
      "reply_count": 0
    },
    {
      "aweme_id": "7378580678356618548",
      "cid": "7378630148738351899",
      "text": "[捂脸]",
      "create_time": "1717971216",
      "user_nickname": "不入戏🍃",
      "user_avatar": "avatars/2024/b1c63b50c7e6fca24e993623aa654f61.jpeg",
      "reply_comment_total": "0",
      "ip_label": "云南",
      "create_time_str": "2024-06-09 22:13",
      "replies": [],
      "reply_count": 0
    },
    {
      "aweme_id": "7378580678356618548",
      "cid": "7378626822722683657",
      "text": "[疑问]",
      "create_time": "1717970442",
      "user_nickname": "(哎呦喂）",
      "user_avatar": "avatars/2024/c8e3c80b735f1eb7a076b7a1f36ec9c9.jpeg",
      "reply_comment_total": "0",
      "ip_label": "河南",
      "create_time_str": "2024-06-09 22:00",
      "replies": [],
      "reply_count": 0
    },
    {
      "aweme_id": "7378580678356618548",
      "cid": "7378622521493504805",
      "text": "这是没有作品发了吗？[捂脸][捂脸][捂脸][捂脸]",
      "create_time": "1717969443",
      "user_nickname": "♥哥谁都怼♥",
      "user_avatar": "avatars/2024/c79109186c601543d6aafde6bd391b77.jpeg",
      "reply_comment_total": "0",
      "ip_label": "广东",
      "create_time_str": "2024-06-09 21:44",
      "replies": [],
      "reply_count": 0
    },
    {
      "aweme_id": "7378580678356618548",
      "cid": "7378622083377414924",
      "text": "我居然看了三遍[尬笑]",
      "create_time": "1717969341",
      "user_nickname": "🌈滨滨有你",
      "user_avatar": "avatars/2024/18d6999100701793886bbc3e6ce69f44.jpeg",
      "reply_comment_total": "0",
      "ip_label": "黑龙江",
      "create_time_str": "2024-06-09 21:42",
      "replies": [],
      "reply_count": 0
    },
    {
      "aweme_id": "7378580678356618548",
      "cid": "7378616906444358427",
      "text": "么么哒",
      "create_time": "1717968137",
      "user_nickname": "无风无痕，只恋",
      "user_avatar": "avatars/2024/7885db01191b67beb408ee827eed1c57.jpeg",
      "reply_comment_total": "0",
      "ip_label": "浙江",
      "create_time_str": "2024-06-09 21:22",
      "replies": [],
      "reply_count": 0
    },
    {
      "aweme_id": "7378580678356618548",
      "cid": "7378616617833661211",
      "text": "[玫瑰][玫瑰][玫瑰][玫瑰][玫瑰][玫瑰][玫瑰]",
      "create_time": "1717968067",
      "user_nickname": "无风无痕，只恋",
      "user_avatar": "avatars/2024/7885db01191b67beb408ee827eed1c57.jpeg",
      "reply_comment_total": "0",
      "ip_label": "浙江",
      "create_time_str": "2024-06-09 21:21",
      "replies": [],
      "reply_count": 0
    },
    {
      "aweme_id": "7378580678356618548",
      "cid": "7378612135776027431",
      "text": "熬夜？一个能打的都没有[二哈]",
      "create_time": "1717967032",
      "user_nickname": "农家烟火✰土菜馆",
      "user_avatar": "avatars/2024/0b2b772e2e24dcad097d5d691199c323.jpeg",
      "reply_comment_total": "0",
      "ip_label": "河北",
      "create_time_str": "2024-06-09 21:03",
      "replies": [],
      "reply_count": 0
    },
    {
      "aweme_id": "7378580678356618548",
      "cid": "7378611501248561983",
      "text": "梦回4399小游戏",
      "create_time": "1717966883",
      "user_nickname": "Kiwi",
      "user_avatar": "avatars/2024/dc5810b1b1c3a63a7910c5c301beb7fa.jpeg",
      "reply_comment_total": "0",
      "ip_label": "英国",
      "create_time_str": "2024-06-09 21:01",
      "replies": [],
      "reply_count": 0
    },
    {
      "aweme_id": "7378580678356618548",
      "cid": "7378604750693401381",
      "text": "？？？[九转大肠]",
      "create_time": "1717965321",
      "user_nickname": "风沙迷了眼⁵¹⁰⁷⁴",
      "user_avatar": "avatars/2024/4edfeaec5cbebf2b198566d0a8617dc1.jpeg",
      "reply_comment_total": "0",
      "ip_label": "广东",
      "create_time_str": "2024-06-09 20:35",
      "replies": [],
      "reply_count": 0
    },
    {
      "aweme_id": "7378580678356618548",
      "cid": "7378599222197175092",
      "text": "你得多无聊，大半夜的[捂脸]",
      "create_time": "1717964035",
      "user_nickname": "Sir 郭",
      "user_avatar": "avatars/2024/f6a5429bead8ac7262cfa20bd002410d.jpeg",
      "reply_comment_total": "0",
      "ip_label": "广西",
      "create_time_str": "2024-06-09 20:13",
      "replies": [],
      "reply_count": 0
    },
    {
      "aweme_id": "7378580678356618548",
      "cid": "7378598329787155209",
      "text": "谁家傻子跑出来了[暗中观察]",
      "create_time": "1717963815",
      "user_nickname": "嘿痞",
      "user_avatar": "avatars/2024/6f4df3226e2156fe85bbb842722ddfa9.jpeg",
      "reply_comment_total": "0",
      "ip_label": "福建",
      "create_time_str": "2024-06-09 20:10",
      "replies": [],
      "reply_count": 0
    },
    {
      "aweme_id": "7378580678356618548",
      "cid": "7378595709547021096",
      "text": "爱播秃头小宝贝又没睡觉[看]",
      "create_time": "1717963216",
      "user_nickname": "小主角",
      "user_avatar": "avatars/2024/33aa68928e77c64dd7e6eb69e8094db0.jpeg",
      "reply_comment_total": "0",
      "ip_label": "江苏",
      "create_time_str": "2024-06-09 20:00",
      "replies": [],
      "reply_count": 0
    },
    {
      "aweme_id": "7378580678356618548",
      "cid": "7378594633967829797",
      "text": "",
      "create_time": "1717962959",
      "user_nickname": "一只小老虎⁵¹⁰⁷⁴🐯",
      "user_avatar": "avatars/2024/af8352c6f23a4de7a91e204f832736f0.jpeg",
      "reply_comment_total": "0",
      "ip_label": "中国台湾",
      "create_time_str": "2024-06-09 19:55",
      "replies": [],
      "reply_count": 0
    },
    {
      "aweme_id": "7378580678356618548",
      "cid": "7378594323682427686",
      "text": "游戏天才还不睡觉[看]",
      "create_time": "1717962894",
      "user_nickname": "爱窥探其他人幸福的小丑",
      "user_avatar": "avatars/2024/27f699abba4a0f8b767ae724d59c7348.jpeg",
      "reply_comment_total": "0",
      "ip_label": "广西",
      "create_time_str": "2024-06-09 19:54",
      "replies": [],
      "reply_count": 0
    },
    {
      "aweme_id": "7378580678356618548",
      "cid": "7378593982408426280",
      "text": "这家伙就是游戏天才",
      "create_time": "1717962815",
      "user_nickname": "🌈LiECheng",
      "user_avatar": "avatars/2024/4eff74385189f8b958631038c156c9c3.jpeg",
      "reply_comment_total": "0",
      "ip_label": "广东",
      "create_time_str": "2024-06-09 19:53",
      "replies": [],
      "reply_count": 0
    },
    {
      "aweme_id": "7378580678356618548",
      "cid": "7378591976609137458",
      "text": "饱饱还不睡，是不是小游戏玩的睡不着[看]",
      "create_time": "1717962351",
      "user_nickname": "宬澜.",
      "user_avatar": "avatars/2024/a2220027101be846815f701023a77e73.jpeg",
      "reply_comment_total": "0",
      "ip_label": "广东",
      "create_time_str": "2024-06-09 19:45",
      "replies": [],
      "reply_count": 0
    },
    {
      "aweme_id": "7378580678356618548",
      "cid": "7378590903365436198",
      "text": "坐等君雅橱窗卖假发[微笑][微笑]",
      "create_time": "1717962095",
      "user_nickname": "SuperSuper--qi",
      "user_avatar": "avatars/2024/da278708c7de1d75eb6c8a809a3219be.jpeg",
      "reply_comment_total": "0",
      "ip_label": "天津",
      "create_time_str": "2024-06-09 19:41",
      "replies": [],
      "reply_count": 0
    },
    {
      "aweme_id": "7378580678356618548",
      "cid": "7378590726902940451",
      "text": "大房也是时候找个[呲牙][呲牙]",
      "create_time": "1717962061",
      "user_nickname": "丶Marsご绝版",
      "user_avatar": "avatars/2024/2b51022c61252e41c750fe6ab029a77b.jpeg",
      "reply_comment_total": "0",
      "ip_label": "安徽",
      "create_time_str": "2024-06-09 19:41",
      "replies": [],
      "reply_count": 0
    },
    {
      "aweme_id": "7378580678356618548",
      "cid": "7378589635784934159",
      "text": "你好像个傻子[捂脸][捂脸][捂脸][捂脸]",
      "create_time": "1717961815",
      "user_nickname": "小野猫ᰔᩚ ⁵¹⁰⁷⁴",
      "user_avatar": "avatars/2024/3d213f039aa7d146acc896eff0cae81a.jpeg",
      "reply_comment_total": "2",
      "ip_label": "四川",
      "create_time_str": "2024-06-09 19:36",
      "replies": [
        {
          "aweme_id": "7378580678356618548",
          "cid": "7378592169165210407",
          "reply_id": "7378589635784934159",
          "reply_to_reply_id": "0",
          "text": "确实很像我外婆家的2傻子[捂脸]",
          "create_time": "1717962401",
          "user_nickname": "骑着🐢追飞机",
          "user_avatar": "avatars/2024/172d228ae92fe9443fdc87332d8565d8.jpeg",
          "reply_to_username": "",
          "ip_label": "广东",
          "create_time_str": "2024-06-09 19:46"
        },
        {
          "aweme_id": "7378580678356618548",
          "cid": "7378635363701064460",
          "reply_id": "7378589635784934159",
          "reply_to_reply_id": "0",
          "text": "小野猫，你居然骂你张大宝贝，小心拉你对掏揍你一顿[捂脸]",
          "create_time": "1717972428",
          "user_nickname": "ら孤痞",
          "user_avatar": "avatars/2024/78750c2816971caf8b2d1e322a6eb282.jpeg",
          "reply_to_username": "",
          "ip_label": "广东",
          "create_time_str": "2024-06-09 22:33"
        }
      ],
      "reply_count": 2
    },
    {
      "aweme_id": "7378580678356618548",
      "cid": "7378588245632680745",
      "text": "说吧 玩了多少次啊",
      "create_time": "1717961481",
      "user_nickname": "愛小野貓",
      "user_avatar": "avatars/2024/2adb3b018c98bb1792e69e7b35f4d139.jpeg",
      "reply_comment_total": "0",
      "ip_label": "河北",
      "create_time_str": "2024-06-09 19:31",
      "replies": [],
      "reply_count": 0
    },
    {
      "aweme_id": "7378580678356618548",
      "cid": "7378588232281490176",
      "text": "起来晨跑了[看][看][看]",
      "create_time": "1717961471",
      "user_nickname": "༊ღ᭄初相遇（拖鞋版）",
      "user_avatar": "avatars/2024/6972daec5ee905a1d8ccd9031e270c31.jpeg",
      "reply_comment_total": "0",
      "ip_label": "广东",
      "create_time_str": "2024-06-09 19:31",
      "replies": [],
      "reply_count": 0
    },
    {
      "aweme_id": "7378580678356618548",
      "cid": "7378587885970785060",
      "text": "",
      "create_time": "1717961395",
      "user_nickname": "敬余生i",
      "user_avatar": "avatars/2024/49bcb3172104242f5c3cbd1b7a2ecc2d.jpeg",
      "reply_comment_total": "0",
      "ip_label": "辽宁",
      "create_time_str": "2024-06-09 19:29",
      "replies": [],
      "reply_count": 0
    },
    {
      "aweme_id": "7378580678356618548",
      "cid": "7378587829422899994",
      "text": "秃头小宝贝👩🏻‍🦲👩🏻‍🦲还没睡[捂脸]",
      "create_time": "1717961377",
      "user_nickname": "🌈烟",
      "user_avatar": "avatars/2024/bb5cdf3186862a9cca18f5b5ece48222.jpeg",
      "reply_comment_total": "0",
      "ip_label": "陕西",
      "create_time_str": "2024-06-09 19:29",
      "replies": [],
      "reply_count": 0
    },
    {
      "aweme_id": "7378580678356618548",
      "cid": "7378586834484085543",
      "text": "幼稚[打脸]",
      "create_time": "1717961152",
      "user_nickname": "某某.",
      "user_avatar": "avatars/2024/e8664e43faf86f3e416758c45c7613df.jpeg",
      "reply_comment_total": "0",
      "ip_label": "重庆",
      "create_time_str": "2024-06-09 19:25",
      "replies": [],
      "reply_count": 0
    },
    {
      "aweme_id": "7378580678356618548",
      "cid": "7378586028212863784",
      "text": "说实话，这游戏天赋不是白吹的",
      "create_time": "1717960966",
      "user_nickname": "用户9501913269808",
      "user_avatar": "avatars/2024/2f0c1d624595a7527daa35a19cf309de.jpeg",
      "reply_comment_total": "0",
      "ip_label": "广东",
      "create_time_str": "2024-06-09 19:22",
      "replies": [],
      "reply_count": 0
    },
    {
      "aweme_id": "7378580678356618548",
      "cid": "7378585921799553843",
      "text": "这是想男人了，睡不着的节奏[捂脸][捂脸]",
      "create_time": "1717960944",
      "user_nickname": "名酒之家",
      "user_avatar": "avatars/2024/4845b7c575318377d3042c547391adfe.jpeg",
      "reply_comment_total": "0",
      "ip_label": "新疆",
      "create_time_str": "2024-06-09 19:22",
      "replies": [],
      "reply_count": 0
    },
    {
      "aweme_id": "7378580678356618548",
      "cid": "7378585856184451876",
      "text": "[疑问]",
      "create_time": "1717960929",
      "user_nickname": "小浪——",
      "user_avatar": "avatars/2024/7ad5acc00512788f81314722ab91557d.jpeg",
      "reply_comment_total": "0",
      "ip_label": "广东",
      "create_time_str": "2024-06-09 19:22",
      "replies": [],
      "reply_count": 0
    },
    {
      "aweme_id": "7378580678356618548",
      "cid": "7378585705297396490",
      "text": "好好好[鼓掌][鼓掌]",
      "create_time": "1717960878",
      "user_nickname": "荆门涛",
      "user_avatar": "avatars/2024/71eefdf83200ddf80035c70096a5a699.jpeg",
      "reply_comment_total": "0",
      "ip_label": "湖北",
      "create_time_str": "2024-06-09 19:21",
      "replies": [],
      "reply_count": 0
    },
    {
      "aweme_id": "7378580678356618548",
      "cid": "7378585601077658402",
      "text": "妹啊，你是真的不睡啊。",
      "create_time": "1717960865",
      "user_nickname": "红豆生北国",
      "user_avatar": "avatars/2024/48c7cf2f97d7ad588b274a45a611dab3.jpeg",
      "reply_comment_total": "0",
      "ip_label": "广西",
      "create_time_str": "2024-06-09 19:21",
      "replies": [],
      "reply_count": 0
    },
    {
      "aweme_id": "7378580678356618548",
      "cid": "7378585521163764517",
      "text": "开播！",
      "create_time": "1717960843",
      "user_nickname": "蹦，沙卡拉卡",
      "user_avatar": "avatars/2024/fa135df7b20e990b692361f553835cc4.jpeg",
      "reply_comment_total": "0",
      "ip_label": "湖南",
      "create_time_str": "2024-06-09 19:20",
      "replies": [],
      "reply_count": 0
    },
    {
      "aweme_id": "7378580678356618548",
      "cid": "7378584790046851891",
      "text": "我看着我也行",
      "create_time": "1717960679",
      "user_nickname": "张全蛋的小心肝。",
      "user_avatar": "avatars/2024/984f82d3e10b8a84628d574ef3279057.jpeg",
      "reply_comment_total": "0",
      "ip_label": "浙江",
      "create_time_str": "2024-06-09 19:17",
      "replies": [],
      "reply_count": 0
    },
    {
      "aweme_id": "7378580678356618548",
      "cid": "7378584481764786959",
      "text": "爱播咋还不睡觉呢[看]",
      "create_time": "1717960610",
      "user_nickname": "酷妞很困🐼",
      "user_avatar": "avatars/2024/4f43cb33db80c0cc45c1fa9772ea4ff6.jpeg",
      "reply_comment_total": "0",
      "ip_label": "云南",
      "create_time_str": "2024-06-09 19:16",
      "replies": [],
      "reply_count": 0
    },
    {
      "aweme_id": "7378580678356618548",
      "cid": "7378584459715429158",
      "text": "我滴乖乖，你还不睡[绝望的凝视]",
      "create_time": "1717960600",
      "user_nickname": "椆柒",
      "user_avatar": "avatars/2024/59f68657116eed575b1c0ac3f339119f.jpeg",
      "reply_comment_total": "0",
      "ip_label": "福建",
      "create_time_str": "2024-06-09 19:16",
      "replies": [],
      "reply_count": 0
    },
    {
      "aweme_id": "7378580678356618548",
      "cid": "7378584422855852841",
      "text": "",
      "create_time": "1717960592",
      "user_nickname": "☀向阳而生",
      "user_avatar": "avatars/2024/f3e89177e47d63cb84226cfdf76b6d81.jpeg",
      "reply_comment_total": "0",
      "ip_label": "重庆",
      "create_time_str": "2024-06-09 19:16",
      "replies": [],
      "reply_count": 0
    },
    {
      "aweme_id": "7378580678356618548",
      "cid": "7378584030668112655",
      "text": "",
      "create_time": "1717960510",
      "user_nickname": "没什么好说的。",
      "user_avatar": "avatars/2024/f4b18f5a10d4814db87fc7b0e96f7422.jpeg",
      "reply_comment_total": "0",
      "ip_label": "广东",
      "create_time_str": "2024-06-09 19:15",
      "replies": [],
      "reply_count": 0
    },
    {
      "aweme_id": "7378580678356618548",
      "cid": "7378583793122853632",
      "text": "",
      "create_time": "1717960445",
      "user_nickname": "·",
      "user_avatar": "avatars/2024/d587d4a158438c79f1c26693c0a8da2b.jpeg",
      "reply_comment_total": "0",
      "ip_label": "重庆",
      "create_time_str": "2024-06-09 19:14",
      "replies": [],
      "reply_count": 0
    },
    {
      "aweme_id": "7378580678356618548",
      "cid": "7378583343320875815",
      "text": "",
      "create_time": "1717960326",
      "user_nickname": "耗门炭烤",
      "user_avatar": "avatars/2024/94ca3cae97a7498d7759f34748bf8b2e.jpeg",
      "reply_comment_total": "0",
      "ip_label": "广东",
      "create_time_str": "2024-06-09 19:12",
      "replies": [],
      "reply_count": 0
    },
    {
      "aweme_id": "7378580678356618548",
      "cid": "7378583188858651433",
      "text": "爱播是不是牙疼",
      "create_time": "1717960312",
      "user_nickname": "用户5830945685154",
      "user_avatar": "avatars/2024/2f0c1d624595a7527daa35a19cf309de.jpeg",
      "reply_comment_total": "1",
      "ip_label": "安徽",
      "create_time_str": "2024-06-09 19:11",
      "replies": [
        {
          "aweme_id": "7378580678356618548",
          "cid": "7378584732933079834",
          "reply_id": "7378583188858651433",
          "reply_to_reply_id": "0",
          "text": "百分百确定牙疼[憨笑]",
          "create_time": "1717960672",
          "user_nickname": "不見鹿🦌",
          "user_avatar": "avatars/2024/5f233c501daee34eeb60952b46cfa2b7.jpeg",
          "reply_to_username": "",
          "ip_label": "浙江",
          "create_time_str": "2024-06-09 19:17"
        }
      ],
      "reply_count": 1
    },
    {
      "aweme_id": "7378580678356618548",
      "cid": "7378582996070613796",
      "text": "你这是半夜想啥那啥呢[尬笑]",
      "create_time": "1717960254",
      "user_nickname": "🐔🦆一如既往🐟",
      "user_avatar": "avatars/2024/63e6fafa7de4fc89eb2fdd3691a96b27.jpeg",
      "reply_comment_total": "1",
      "ip_label": "上海",
      "create_time_str": "2024-06-09 19:10",
      "replies": [
        {
          "aweme_id": "7378580678356618548",
          "cid": "7378584645916902182",
          "reply_id": "7378582996070613796",
          "reply_to_reply_id": "0",
          "text": "牙疼睡不着[憨笑][憨笑]",
          "create_time": "1717960632",
          "user_nickname": "不見鹿🦌",
          "user_avatar": "avatars/2024/5f233c501daee34eeb60952b46cfa2b7.jpeg",
          "reply_to_username": "",
          "ip_label": "浙江",
          "create_time_str": "2024-06-09 19:17"
        }
      ],
      "reply_count": 1
    },
    {
      "aweme_id": "7378580678356618548",
      "cid": "7378582889825534729",
      "text": "太奶",
      "create_time": "1717960232",
      "user_nickname": "哈利波特大",
      "user_avatar": "avatars/2024/f84bb86a93fd1c851acae42d83530aa3.jpeg",
      "reply_comment_total": "0",
      "ip_label": "湖南",
      "create_time_str": "2024-06-09 19:10",
      "replies": [],
      "reply_count": 0
    },
    {
      "aweme_id": "7378580678356618548",
      "cid": "7378539828294189878",
      "text": "他俩不要谢谢你",
      "create_time": "1717960204",
      "user_nickname": "随性",
      "user_avatar": "avatars/2024/57b46797cbd1f245ee33af858ae93ee6.jpeg",
      "reply_comment_total": "0",
      "ip_label": "河南",
      "create_time_str": "2024-06-09 19:10",
      "replies": [],
      "reply_count": 0
    },
    {
      "aweme_id": "7378580678356618548",
      "cid": "7378582685919216424",
      "text": "真优质[看]",
      "create_time": "1717960188",
      "user_nickname": "爱了&爱了",
      "user_avatar": "avatars/2024/394a65c0d44d97525c4ec2144e658a89.jpeg",
      "reply_comment_total": "0",
      "ip_label": "广东",
      "create_time_str": "2024-06-09 19:09",
      "replies": [],
      "reply_count": 0
    },
    {
      "aweme_id": "7378580678356618548",
      "cid": "7378582536509997850",
      "text": "快睡觉！头发都要没了。",
      "create_time": "1717960156",
      "user_nickname": "@🌈星星✨️✨",
      "user_avatar": "avatars/2024/adb603d60b7458ce27d2f22c85507ef8.jpeg",
      "reply_comment_total": "0",
      "ip_label": "广东",
      "create_time_str": "2024-06-09 19:09",
      "replies": [],
      "reply_count": 0
    },
    {
      "aweme_id": "7378580678356618548",
      "cid": "7378582569329476379",
      "text": "不睡觉啊[捂脸][捂脸][捂脸]",
      "create_time": "1717960150",
      "user_nickname": "用户5655091545561",
      "user_avatar": "avatars/2024/2f0c1d624595a7527daa35a19cf309de.jpeg",
      "reply_comment_total": "0",
      "ip_label": "安徽",
      "create_time_str": "2024-06-09 19:09",
      "replies": [],
      "reply_count": 0
    },
    {
      "aweme_id": "7378580678356618548",
      "cid": "7378582558256169762",
      "text": "饱饱，还不睡，",
      "create_time": "1717960149",
      "user_nickname": "孙生",
      "user_avatar": "avatars/2024/2d8bcbd4160e7cdf1d0e23c9f85474d7.jpeg",
      "reply_comment_total": "0",
      "ip_label": "广东",
      "create_time_str": "2024-06-09 19:09",
      "replies": [],
      "reply_count": 0
    },
    {
      "aweme_id": "7378580678356618548",
      "cid": "7378582392293311273",
      "text": "你开直播玩 我们也能看",
      "create_time": "1717960126",
      "user_nickname": "ᰔᰮ冷訫²⁰²⁴/₉.₁₈ᵕ̈",
      "user_avatar": "avatars/2024/8373dfbb824da20f7bd3a2100c85184b.jpeg",
      "reply_comment_total": "0",
      "ip_label": "安徽",
      "create_time_str": "2024-06-09 19:08",
      "replies": [],
      "reply_count": 0
    },
    {
      "aweme_id": "7378580678356618548",
      "cid": "7378582352619160359",
      "text": "？？？？",
      "create_time": "1717960110",
      "user_nickname": "First encounter",
      "user_avatar": "avatars/2024/737794f8bb2bd308deede47d0d6dd93c.jpeg",
      "reply_comment_total": "0",
      "ip_label": "北京",
      "create_time_str": "2024-06-09 19:08",
      "replies": [],
      "reply_count": 0
    },
    {
      "aweme_id": "7378580678356618548",
      "cid": "7378582273232995082",
      "text": "我真是服了你了，大晚上玩这个",
      "create_time": "1717960085",
      "user_nickname": "🌈枫",
      "user_avatar": "avatars/2024/0a9edf50f158c0147387b98b832514ec.jpeg",
      "reply_comment_total": "0",
      "ip_label": "福建",
      "create_time_str": "2024-06-09 19:08",
      "replies": [],
      "reply_count": 0
    },
    {
      "aweme_id": "7378580678356618548",
      "cid": "7378582153531196201",
      "text": "不睡觉干嘛呢这 [打脸][打脸][打脸]",
      "create_time": "1717960053",
      "user_nickname": "小蓝同学",
      "user_avatar": "avatars/2024/7b4cd54feeda73439345dcc70f1be044.jpeg",
      "reply_comment_total": "1",
      "ip_label": "北京",
      "create_time_str": "2024-06-09 19:07",
      "replies": [
        {
          "aweme_id": "7378580678356618548",
          "cid": "7378584726183625522",
          "reply_id": "7378582153531196201",
          "reply_to_reply_id": "0",
          "text": "牙疼睡不着[憨笑]",
          "create_time": "1717960655",
          "user_nickname": "不見鹿🦌",
          "user_avatar": "avatars/2024/5f233c501daee34eeb60952b46cfa2b7.jpeg",
          "reply_to_username": "",
          "ip_label": "浙江",
          "create_time_str": "2024-06-09 19:17"
        }
      ],
      "reply_count": 1
    },
    {
      "aweme_id": "7378580678356618548",
      "cid": "7378581970089673524",
      "text": "小姐姐你…[尬笑]",
      "create_time": "1717960016",
      "user_nickname": "a睡不醒",
      "user_avatar": "avatars/2024/336f0bee604c27f7dbcea8586ca09ef5.jpeg",
      "reply_comment_total": "0",
      "ip_label": "甘肃",
      "create_time_str": "2024-06-09 19:06",
      "replies": [],
      "reply_count": 0
    },
    {
      "aweme_id": "7378580678356618548",
      "cid": "7378581852947481379",
      "text": "[发呆][发呆]",
      "create_time": "1717959999",
      "user_nickname": "橙橙⁷²⁹（晴书团队）",
      "user_avatar": "avatars/2024/131b156ed25112abba0fa8fb35736216.jpeg",
      "reply_comment_total": "0",
      "ip_label": "四川",
      "create_time_str": "2024-06-09 19:06",
      "replies": [],
      "reply_count": 0
    },
    {
      "aweme_id": "7378580678356618548",
      "cid": "7378581877538030386",
      "text": "爱播几点了还不睡觉",
      "create_time": "1717959990",
      "user_nickname": "呢呦牛",
      "user_avatar": "avatars/2024/6c84e6c96e945ed62fe8053529801c33.jpeg",
      "reply_comment_total": "0",
      "ip_label": "山西",
      "create_time_str": "2024-06-09 19:06",
      "replies": [],
      "reply_count": 0
    },
    {
      "aweme_id": "7378580678356618548",
      "cid": "7378581218109850402",
      "text": "妳不睡在那边玩这个游戏",
      "create_time": "1717959845",
      "user_nickname": "🦁🖤",
      "user_avatar": "avatars/2024/fcf3a29d874db4fecba597291c16c93d.jpeg",
      "reply_comment_total": "0",
      "ip_label": "中国台湾",
      "create_time_str": "2024-06-09 19:04",
      "replies": [],
      "reply_count": 0
    },
    {
      "aweme_id": "7378580678356618548",
      "cid": "7378581195075273491",
      "text": "？？？不睡你有本事就开播！[咒骂][打脸]",
      "create_time": "1717959837",
      "user_nickname": "認生若如初見",
      "user_avatar": "avatars/2024/c8b0cdc9eacbdf6dfc089e0c4410d662.jpeg",
      "reply_comment_total": "0",
      "ip_label": "广东",
      "create_time_str": "2024-06-09 19:03",
      "replies": [],
      "reply_count": 0
    },
    {
      "aweme_id": "7378580678356618548",
      "cid": "7378581090703885090",
      "text": "[捂脸][捂脸][捂脸]",
      "create_time": "1717959815",
      "user_nickname": "懒仙",
      "user_avatar": "avatars/2024/7bd8f1351fab4924963f3a89103f66fd.jpeg",
      "reply_comment_total": "0",
      "ip_label": "海南",
      "create_time_str": "2024-06-09 19:03",
      "replies": [],
      "reply_count": 0
    },
    {
      "aweme_id": "7378580678356618548",
      "cid": "7378581048681300786",
      "text": "[比心][比心][比心]游戏天才“少女”",
      "create_time": "1717959804",
      "user_nickname": "用户1368639900961",
      "user_avatar": "avatars/2024/2f0c1d624595a7527daa35a19cf309de.jpeg",
      "reply_comment_total": "0",
      "ip_label": "葡萄牙",
      "create_time_str": "2024-06-09 19:03",
      "replies": [],
      "reply_count": 0
    }
  ]
}